Metadata-Version: 2.1
Name: borg-pod
Version: 1.0.11
Summary: A lightweight, decoupled wrapper for dynamic class assignment.
Home-page: https://github.com/Andrew-Hogan/borg_pod
Author: Andrew M. Hogan
Author-email: drewthedruid@gmail.com
License: LICENSE
Platform: any
Classifier: Intended Audience :: Developers
Classifier: Programming Language :: Python :: 3
Classifier: Programming Language :: Python
Classifier: License :: OSI Approved :: Apache Software License
Classifier: Operating System :: OS Independent
Classifier: Topic :: Software Development :: Libraries :: Python Modules
Classifier: Topic :: Utilities
